[
  {
    "id": "arcon:mount_360",
    "translate_key_desc": "mount",
    "tab": "weapons",
    "image": "mount360.png"
  },
  {
    "id": "arcon:mount_270",
    "translate_key_desc": "mount",
    "tab": "weapons",
    "image": "mount300.png"
  },
  {
    "id": "arcon:mount_180",
    "translate_key_desc": "mount",
    "tab": "weapons",
    "image": "mount180.png"
  },
  {
    "id": "arcon:mount_90",
    "translate_key_desc": "mount",
    "tab": "weapons",
    "image": "mount90.png"
  },
  {
    "id": "arcon:mount_30",
    "translate_key_desc": "mount",
    "tab": "weapons",
    "image": "mount30.png"
  },
  {
    "id": "arcon:mount_360_micro",
    "tab": "weapons",
    "image": "mount360short.png"
  },
  {
    "id": "arcon:mount_10_range",
    "tab": "weapons",
    "image": "mount10range.png"
  },
  {
    "id": "arcon:mount_10_demi",
    "tab": "weapons",
    "image": "mount10wide.png"
  },
  {
    "id": "arcon:drone_body",
    "disabled": true,
    "tab": "weapons",
    "image": "droneBody.png"
  },
  {
    "id": "arcon:pad_2x2",
    "disabled": true,
    "tab": "armor",
    "image": "pad2x2.png"
  },
  {
    "id": "arcon:armor_heavy_2x2",
    "translate_key_name": "armor_heavy",
    "translate_key_desc": "armor_heavy",
    "tab": "armor1",
    "image": "HArmor2x2.png"
  },
  {
    "id": "arcon:armor_heavy_1x2",
    "translate_key_name": "armor_heavy",
    "translate_key_desc": "armor_heavy",
    "tab": "armor1",
    "image": "HArmor1x2.png"
  },
  {
    "id": "arcon:armor_heavy_1x1",
    "translate_key_name": "armor_heavy",
    "translate_key_desc": "armor_heavy",
    "tab": "armor1",
    "image": "HArmor1x1.png"
  },
  {
    "id": "arcon:armor_heavy_2x1",
    "translate_key_name": "armor_heavy",
    "translate_key_desc": "armor_heavy",
    "tab": "armor1",
    "image": "HArmor2x1.png"
  },
  {
    "id": "arcon:armor_heavy_1x1_angle",
    "translate_key_name": "armor_heavy",
    "translate_key_desc": "armor_heavy",
    "tab": "armor1",
    "image": "HArmor1x1Angle.png"
  },
  {
    "id": "arcon:armor_heavy_1x1_angle_back",
    "translate_key_name": "armor_heavy",
    "translate_key_desc": "armor_heavy",
    "tab": "armor1",
    "image": "HArmor1x1AngleBack.png"
  },
  {
    "id": "arcon:armor_heavy_2x2_angle",
    "translate_key_name": "armor_heavy",
    "translate_key_desc": "armor_heavy",
    "tab": "armor1",
    "image": "HArmor2x2Angle.png"
  },
  {
    "id": "arcon:armor_heavy_2x2_angle_back",
    "translate_key_name": "armor_heavy",
    "translate_key_desc": "armor_heavy",
    "tab": "armor1",
    "image": "HArmor2x2AngleBack.png"
  },
  {
    "id": "arcon:armor_heavy_2x2_front_1",
    "translate_key_name": "armor_heavy",
    "translate_key_desc": "armor_heavy",
    "tab": "armor1",
    "image": "HArmor2x2Front1.png"
  },
  {
    "id": "arcon:armor_heavy_2x2_front_2",
    "translate_key_name": "armor_heavy",
    "translate_key_desc": "armor_heavy",
    "tab": "armor1",
    "image": "HArmor2x2Front2.png"
  },
  {
    "id": "arcon:armor_heavy_1x2_front_1",
    "translate_key_name": "armor_heavy",
    "translate_key_desc": "armor_heavy",
    "tab": "armor1",
    "image": "HArmor1x2Font1.png"
  },
  {
    "id": "arcon:armor_heavy_1x2_front_2",
    "translate_key_name": "armor_heavy",
    "translate_key_desc": "armor_heavy",
    "tab": "armor1",
    "image": "HArmor1x2Front2.png"
  },
  {
    "id": "arcon:armor_heavy_2x2_back_1",
    "translate_key_name": "armor_heavy",
    "translate_key_desc": "armor_heavy",
    "tab": "armor1",
    "image": "HArmor2x2Back1.png"
  },
  {
    "id": "arcon:armor_heavy_2x2_back_2",
    "translate_key_name": "armor_heavy",
    "translate_key_desc": "armor_heavy",
    "tab": "armor1",
    "image": "HArmor2x2Back2.png"
  },
  {
    "id": "arcon:armor_heavy_1x2_back_1",
    "translate_key_name": "armor_heavy",
    "translate_key_desc": "armor_heavy",
    "tab": "armor1",
    "image": "HArmor1x2Back1.png"
  },
  {
    "id": "arcon:armor_heavy_1x2_back_2",
    "translate_key_name": "armor_heavy",
    "translate_key_desc": "armor_heavy",
    "tab": "armor1",
    "image": "HArmor1x2Back2.png"
  },
  {
    "id": "arcon:armor_heavy_2x2_curved",
    "translate_key_name": "armor_heavy",
    "translate_key_desc": "armor_heavy",
    "tab": "armor1",
    "image": "HArmor2x2Curved.png"
  },
  {
    "id": "arcon:armor_heavy_2x1_curved",
    "translate_key_name": "armor_heavy",
    "translate_key_desc": "armor_heavy",
    "tab": "armor1",
    "image": "HArmor2x1Curved.png"
  },
  {
    "id": "arcon:armor_heavy_1x2_curved",
    "translate_key_name": "armor_heavy",
    "translate_key_desc": "armor_heavy",
    "tab": "armor1",
    "image": "HArmor1x2Curved.png"
  },
  {
    "id": "arcon:armor_heavy_2x2_angle_shadow",
    "translate_key_name": "armor_heavy",
    "translate_key_desc": "armor_heavy",
    "tab": "armor1",
    "image": "ShadowNArmor2x2Angle.png"
  },
  {
    "id": "arcon:armor_heavy_2x2_shadow",
    "translate_key_name": "armor_heavy",
    "translate_key_desc": "armor_heavy",
    "tab": "armor1",
    "image": "ShadowNArmor2x2.png"
  },
  {
    "id": "arcon:armor_heavy_2x1_shadow",
    "translate_key_name": "armor_heavy",
    "translate_key_desc": "armor_heavy",
    "tab": "armor1",
    "image": "ShadowNArmor2x1.png"
  },
  {
    "id": "arcon:armor_heavy_1x1_shadow",
    "translate_key_name": "armor_heavy",
    "translate_key_desc": "armor_heavy",
    "tab": "armor1",
    "image": "ShadowNArmor1x1.png"
  },
  {
    "id": "arcon:armor_heavy_1x2_shadow",
    "translate_key_name": "armor_heavy",
    "translate_key_desc": "armor_heavy",
    "tab": "armor1",
    "image": "ShadowNArmor1x2.png"
  },
  {
    "id": "arcon:armor_heavy_2x2_curved_shadow",
    "translate_key_name": "armor_heavy",
    "translate_key_desc": "armor_heavy",
    "tab": "armor1",
    "image": "ShadowNArmor2x2Curve.png"
  },
  {
    "id": "arcon:armor_heavy_1x1_angle_shadow",
    "translate_key_name": "armor_heavy",
    "translate_key_desc": "armor_heavy",
    "tab": "armor1",
    "image": "ShadowNArmor1x1Angle.png"
  },
  {
    "id": "arcon:armor_heavy_1x1_corner_shadow",
    "translate_key_name": "armor_heavy",
    "translate_key_desc": "armor_heavy",
    "tab": "armor1",
    "image": "ShadowNArmor1x1Corner.png"
  },
  {
    "id": "arcon:armor_heavy_1x1_corner_inner_shadow",
    "translate_key_name": "armor_heavy",
    "translate_key_desc": "armor_heavy",
    "tab": "armor1",
    "image": "ShadowNArmor1x1CornerInner.png"
  },
  {
    "id": "arcon:armor_heavy_2x1_curved_shadow",
    "translate_key_name": "armor_heavy",
    "translate_key_desc": "armor_heavy",
    "tab": "armor1",
    "image": "ShadowNArmor2x1Curved.png"
  },
  {
    "id": "arcon:armor_heavy_1x2_curved_shadow",
    "translate_key_name": "armor_heavy",
    "translate_key_desc": "armor_heavy",
    "tab": "armor1",
    "image": "ShadowNArmor1x2Curved.png"
  },
  {
    "id": "arcon:armor_heavy_1x2_front_1_shadow",
    "translate_key_name": "armor_heavy",
    "translate_key_desc": "armor_heavy",
    "tab": "armor1",
    "image": "ShadowNArmor1x2Font1.png"
  },
  {
    "id": "arcon:armor_ultralight_1x1",
    "translate_key_name": "armor_ultralight",
    "translate_key_desc": "armor_ultralight",
    "tab": "armor3",
    "image": "UArmor1x1.png"
  },
  {
    "id": "arcon:armor_ultralight_1x2",
    "translate_key_name": "armor_ultralight",
    "translate_key_desc": "armor_ultralight",
    "tab": "armor3",
    "image": "UArmor1x2.png"
  },
  {
    "id": "arcon:armor_ultralight_2x1",
    "translate_key_name": "armor_ultralight",
    "translate_key_desc": "armor_ultralight",
    "tab": "armor3",
    "image": "UArmor2x1.png"
  },
  {
    "id": "arcon:armor_ultralight_1x1_angle",
    "translate_key_name": "armor_ultralight",
    "translate_key_desc": "armor_ultralight",
    "tab": "armor3",
    "image": "UArmor1x1Angle.png"
  },
  {
    "id": "arcon:armor_ultralight_1x1_angle_back",
    "translate_key_name": "armor_ultralight",
    "translate_key_desc": "armor_ultralight",
    "tab": "armor3",
    "image": "UArmor1x1AngleBack.png"
  },
  {
    "id": "arcon:armor_ultralight_2x2",
    "translate_key_name": "armor_ultralight",
    "translate_key_desc": "armor_ultralight",
    "tab": "armor3",
    "image": "UArmor2x2.png"
  },
  {
    "id": "arcon:armor_ultralight_1x2_notch_1",
    "translate_key_name": "armor_ultralight",
    "translate_key_desc": "armor_ultralight",
    "tab": "armor3",
    "image": "UArmor1x2Notch1.png"
  },
  {
    "id": "arcon:armor_ultralight_1x2_notch_2",
    "translate_key_name": "armor_ultralight",
    "translate_key_desc": "armor_ultralight",
    "tab": "armor3",
    "image": "UArmor1x2Notch2.png"
  },
  {
    "id": "arcon:armor_ultralight_1x1_notch_1",
    "translate_key_name": "armor_ultralight",
    "translate_key_desc": "armor_ultralight",
    "tab": "armor3",
    "image": "UArmor1x1Notch1.png"
  },
  {
    "id": "arcon:armor_ultralight_1x1_notch_2",
    "translate_key_name": "armor_ultralight",
    "translate_key_desc": "armor_ultralight",
    "tab": "armor3",
    "image": "UArmor1x1Notch2.png"
  },
  {
    "id": "arcon:armor_ultralight_1x1_spike",
    "translate_key_name": "armor_ultralight",
    "translate_key_desc": "armor_ultralight",
    "tab": "armor3",
    "image": "UArmor1x1Spike.png"
  },
  {
    "id": "arcon:armor_volumetric_1x2_side_bar",
    "translate_key_name": "armor_volumetric",
    "translate_key_desc": "armor_volumetric",
    "tab": "armor2",
    "image": "VArmor1x2SideBar.png"
  },
  {
    "id": "arcon:armor_volumetric_1x2_side_bar_filled",
    "translate_key_name": "armor_volumetric",
    "translate_key_desc": "armor_volumetric",
    "tab": "armor2",
    "image": "VArmor1x2SideBarFilled.png"
  },
  {
    "id": "arcon:armor_volumetric_1x2_i_beam",
    "translate_key_name": "armor_volumetric",
    "translate_key_desc": "armor_volumetric",
    "tab": "armor2",
    "image": "VArmor1x2IBeam.png"
  },
  {
    "id": "arcon:armor_volumetric_1x2_corner4",
    "translate_key_name": "armor_volumetric",
    "translate_key_desc": "armor_volumetric",
    "tab": "armor2",
    "image": "VArmor1x2Corner4.png"
  },
  {
    "id": "arcon:armor_volumetric_1x2_end",
    "translate_key_name": "armor_volumetric",
    "translate_key_desc": "armor_volumetric",
    "tab": "armor2",
    "image": "VArmor1x2End.png"
  },
  {
    "id": "arcon:armor_volumetric_1x1_corner1",
    "translate_key_name": "armor_volumetric",
    "translate_key_desc": "armor_volumetric",
    "tab": "armor2",
    "image": "VArmor1x1Corner1.png"
  },
  {
    "id": "arcon:armor_volumetric_1x1_corner2",
    "translate_key_name": "armor_volumetric",
    "translate_key_desc": "armor_volumetric",
    "tab": "armor2",
    "image": "VArmor1x1Corner2.png"
  },
  {
    "id": "arcon:armor_volumetric_1x1_corner3",
    "translate_key_name": "armor_volumetric",
    "translate_key_desc": "armor_volumetric",
    "tab": "armor2",
    "image": "VArmor1x1Corner3.png"
  },
  {
    "id": "arcon:armor_volumetric_1x1_hook",
    "translate_key_name": "armor_volumetric",
    "translate_key_desc": "armor_volumetric",
    "tab": "armor2",
    "image": "VArmor1x1Hook.png"
  },
  {
    "id": "arcon:armor_volumetric_1x1_corner_back",
    "translate_key_name": "armor_volumetric",
    "translate_key_desc": "armor_volumetric",
    "tab": "armor2",
    "image": "VArmor1x1CornerBack.png"
  },
  {
    "id": "arcon:armor_volumetric_2x2",
    "translate_key_name": "armor_volumetric",
    "translate_key_desc": "armor_volumetric",
    "tab": "armor2",
    "image": "VArmor2x2.png"
  },
  {
    "id": "arcon:armor_volumetric_1x2",
    "translate_key_name": "armor_volumetric",
    "translate_key_desc": "armor_volumetric",
    "tab": "armor2",
    "image": "VArmor1x2.png"
  },
  {
    "id": "arcon:armor_volumetric_1x1",
    "translate_key_name": "armor_volumetric",
    "translate_key_desc": "armor_volumetric",
    "tab": "armor2",
    "image": "VArmor1x1.png"
  },
  {
    "id": "arcon:armor_volumetric_1x1_angle",
    "translate_key_name": "armor_volumetric",
    "translate_key_desc": "armor_volumetric",
    "tab": "armor2",
    "image": "VArmor1x1Angle.png"
  },
  {
    "id": "arcon:armor_volumetric_2x2_angle",
    "translate_key_name": "armor_volumetric",
    "translate_key_desc": "armor_volumetric",
    "tab": "armor2",
    "image": "VArmor2x2Angle.png"
  },
  {
    "id": "arcon:armor_volumetric_2x2_curved",
    "translate_key_name": "armor_volumetric",
    "translate_key_desc": "armor_volumetric",
    "tab": "armor2",
    "image": "VArmor2x2Curve.png"
  },
  {
    "id": "arcon:armor_volumetric_1x1_curved",
    "translate_key_name": "armor_volumetric",
    "translate_key_desc": "armor_volumetric",
    "tab": "armor2",
    "image": "VArmor1x1Curve.png"
  },
  {
    "id": "arcon:armor_volumetric_2x1_curved",
    "translate_key_name": "armor_volumetric",
    "translate_key_desc": "armor_volumetric",
    "tab": "armor2",
    "image": "VArmor2x1Curved.png"
  },
  {
    "id": "arcon:armor_volumetric_1x2_curved",
    "translate_key_name": "armor_volumetric",
    "translate_key_desc": "armor_volumetric",
    "tab": "armor2",
    "image": "VArmor1x2Curved.png"
  },
  {
    "id": "arcon:armor_volumetric_2x2_curved",
    "translate_key_name": "armor_volumetric",
    "translate_key_desc": "armor_volumetric",
    "tab": "armor2",
    "image": "VArmor2x2Curved.png"
  },
  {
    "id": "arcon:armor_volumetric_2x2_angle_shadow",
    "translate_key_name": "armor_volumetric",
    "translate_key_desc": "armor_volumetric",
    "tab": "armor2",
    "image": "VShadowNArmor2x2Angle.png"
  },
  {
    "id": "arcon:armor_volumetric_2x2_shadow",
    "translate_key_name": "armor_volumetric",
    "translate_key_desc": "armor_volumetric",
    "tab": "armor2",
    "image": "VShadowNArmor2x2.png"
  },
  {
    "id": "arcon:armor_volumetric_2x1_shadow",
    "translate_key_name": "armor_volumetric",
    "translate_key_desc": "armor_volumetric",
    "tab": "armor2",
    "image": "VShadowNArmor2x1.png"
  },
  {
    "id": "arcon:armor_volumetric_1x1_shadow",
    "translate_key_name": "armor_volumetric",
    "translate_key_desc": "armor_volumetric",
    "tab": "armor2",
    "image": "VShadowNArmor1x1.png"
  },
  {
    "id": "arcon:armor_volumetric_1x2_shadow",
    "translate_key_name": "armor_volumetric",
    "translate_key_desc": "armor_volumetric",
    "tab": "armor2",
    "image": "VShadowNArmor1x2.png"
  },
  {
    "id": "arcon:armor_volumetric_2x2_curved_shadow",
    "translate_key_name": "armor_volumetric",
    "translate_key_desc": "armor_volumetric",
    "tab": "armor2",
    "image": "VShadowNArmor2x2Curve.png"
  },
  {
    "id": "arcon:armor_volumetric_1x1_angle_shadow",
    "translate_key_name": "armor_volumetric",
    "translate_key_desc": "armor_volumetric",
    "tab": "armor2",
    "image": "VShadowNArmor1x1Angle.png"
  },
  {
    "id": "arcon:armor_volumetric_1x1_corner_shadow",
    "translate_key_name": "armor_volumetric",
    "translate_key_desc": "armor_volumetric",
    "tab": "armor2",
    "image": "VShadowNArmor1x1Corner.png"
  },
  {
    "id": "arcon:armor_volumetric_1x1_corner_inner_shadow",
    "translate_key_name": "armor_volumetric",
    "translate_key_desc": "armor_volumetric",
    "tab": "armor2",
    "image": "VShadowNArmor1x1CornerInner.png"
  },
  {
    "id": "arcon:energy_reactor_2x2",
    "translate_key_name": "energy_reactor",
    "translate_key_desc": "energy_reactor",
    "tab": "energy",
    "image": "Reactor2x2.png"
  },
  {
    "id": "arcon:energy_reactor_1x2",
    "translate_key_name": "energy_reactor",
    "translate_key_desc": "energy_reactor",
    "tab": "energy",
    "image": "Reactor1x2.png"
  },
  {
    "id": "arcon:energy_reactor_2x1",
    "translate_key_name": "energy_reactor",
    "translate_key_desc": "energy_reactor",
    "tab": "energy",
    "image": "Reactor2x1.png"
  },
  {
    "id": "arcon:energy_reactor_1x1",
    "translate_key_name": "energy_reactor",
    "translate_key_desc": "energy_reactor",
    "tab": "energy",
    "image": "Reactor1x1.png"
  },
  {
    "id": "arcon:energy_solar_1x1",
    "translate_key_name": "energy_solar",
    "translate_key_desc": "energy_solar",
    "tab": "energy",
    "image": "solar1x1.png"
  },
  {
    "id": "arcon:energy_solar_2x2",
    "translate_key_name": "energy_solar",
    "translate_key_desc": "energy_solar",
    "tab": "energy",
    "image": "solar2x2.png"
  },
  {
    "id": "arcon:energy_solar_3x3",
    "translate_key_name": "energy_solar",
    "translate_key_desc": "energy_solar",
    "tab": "energy",
    "image": "solar3x3.png"
  },
  {
    "id": "arcon:energy_transfer",
    "tab": "energy",
    "image": "EnergyTransfer.png"
  },
  {
    "id": "arcon:stasis_field",
    "tab": "defence",
    "image": "StasisField.png"
  },
  {
    "id": "arcon:supercapital_bridge",
    "disabled": true,
    "tab": "defence",
    "image": "pad4x4.png"
  },
  {
    "id": "arcon:shield_generator_2x2",
    "tab": "defence",
    "image": "Shield2x2.png"
  },
  {
    "id": "arcon:shield_generator_2x1",
    "tab": "defence",
    "image": "Shield2x1.png"
  },
  {
    "id": "arcon:shield_generator_1x1",
    "tab": "defence",
    "image": "Shield1x1.png"
  },
  {
    "id": "arcon:cloak_generator",
    "tab": "defence",
    "image": "CloakGenerator.png"
  },
  {
    "id": "arcon:energy_battery_1x2",
    "translate_key_name": "energy_battery",
    "translate_key_desc": "energy_battery",
    "tab": "energy",
    "image": "Battery1x2.png"
  },
  {
    "id": "arcon:energy_battery_1x1",
    "translate_key_name": "energy_battery",
    "translate_key_desc": "energy_battery",
    "tab": "energy",
    "image": "Battery1x1.png"
  },
  {
    "id": "arcon:energy_battery_2x1",
    "translate_key_name": "energy_battery",
    "translate_key_desc": "energy_battery",
    "tab": "energy",
    "image": "Battery2x1.png"
  },
  {
    "id": "arcon:energy_battery_2x2",
    "translate_key_name": "energy_battery",
    "translate_key_desc": "energy_battery",
    "tab": "energy",
    "image": "Battery2x2.png"
  },
  {
    "id": "arcon:thruster_ultraheavy_2x2",
    "translate_key_name": "thruster_ultraheavy",
    "translate_key_desc": "thruster_ultraheavy",
    "disabled": true,
    "tab": "engines",
    "image": "engine05.png"
  },
  {
    "id": "arcon:thruster_bulk_2x2",
    "translate_key_name": "thruster_bulk",
    "translate_key_desc": "thruster_bulk",
    "tab": "engines",
    "image": "engine09.png"
  },
  {
    "id": "arcon:thruster_bulk_1x3",
    "translate_key_name": "thruster_bulk",
    "translate_key_desc": "thruster_bulk",
    "tab": "engines",
    "image": "engine02.png"
  },
  {
    "id": "arcon:thruster_cruiser_1x3",
    "translate_key_name": "thruster_cruiser",
    "translate_key_desc": "thruster_cruiser",
    "tab": "engines",
    "image": "engine01.png"
  },
  {
    "id": "arcon:thruster_cruiser_2x1",
    "translate_key_name": "thruster_cruiser",
    "translate_key_desc": "thruster_cruiser",
    "tab": "engines",
    "image": "engine08.png"
  },
  {
    "id": "arcon:thruster_scout_1x2",
    "translate_key_name": "thruster_scout",
    "translate_key_desc": "thruster_scout",
    "tab": "engines",
    "image": "engine04.png"
  },
  {
    "id": "arcon:thruster_scout_2x1",
    "translate_key_name": "thruster_scout",
    "translate_key_desc": "thruster_scout",
    "tab": "engines",
    "image": "engine04long.png"
  },
  {
    "id": "arcon:thruster_legacy_engine06",
    "disabled": true,
    "tab": "engines",
    "image": "engine06.png"
  },
  {
    "id": "arcon:thruster_fighter_1x2",
    "translate_key_name": "thruster_fighter",
    "translate_key_desc": "thruster_fighter",
    "tab": "engines",
    "image": "engine03.png"
  },
  {
    "id": "arcon:thruster_fighter_2x1",
    "translate_key_name": "thruster_fighter",
    "translate_key_desc": "thruster_fighter",
    "tab": "engines",
    "image": "engine03long.png"
  },
  {
    "id": "arcon:thruster_ultrafast_2x2",
    "translate_key_name": "thruster_ultrafast",
    "translate_key_desc": "thruster_ultrafast",
    "tab": "engines",
    "image": "engine07.png"
  },
  {
    "id": "arcon:jump_generator",
    "tab": "engines",
    "image": "engineJump.png"
  },
  {
    "id": "arcon:wing_2x2",
    "translate_key_name": "wing",
    "translate_key_desc": "wing",
    "tab": "engines",
    "image": "Wing2x2.png"
  },
  {
    "id": "arcon:wing_1x2",
    "translate_key_name": "wing",
    "translate_key_desc": "wing",
    "tab": "engines",
    "image": "Wing1x2.png"
  },
  {
    "id": "arcon:wing_2x1",
    "translate_key_name": "wing",
    "translate_key_desc": "wing",
    "tab": "engines",
    "image": "Wing2x1.png"
  },
  {
    "id": "arcon:wing_1x1_angle",
    "translate_key_name": "wing",
    "translate_key_desc": "wing",
    "tab": "engines",
    "image": "Wing1x1Angle.png"
  },
  {
    "id": "arcon:wing_1x1_round",
    "translate_key_name": "wing",
    "translate_key_desc": "wing",
    "tab": "engines",
    "image": "Wing1x1Round.png"
  },
  {
    "id": "arcon:wing_1x1_notch",
    "translate_key_name": "wing",
    "translate_key_desc": "wing",
    "tab": "engines",
    "image": "Wing1x1Notch.png"
  },
  {
    "id": "arcon:weapon_pd_beam",
    "tab": "weapons",
    "image": "turHex2.png"
  },
  {
    "id": "arcon:weapon_pd_buckshot",
    "tab": "weapons",
    "image": "turHex1.png"
  },
  {
    "id": "arcon:weapon_fusion_ring_dispenser",
    "tab": "weapons",
    "image": "turRing.png"
  },
  {
    "id": "arcon:weapon_legacy_kinetic_ram",
    "disabled": true,
    "tab": "weapons",
    "image": "turWavePush.png"
  },
  {
    "id": "arcon:weapon_torpedo_launcher",
    "tab": "weapons",
    "image": "turTorp.png"
  },
  {
    "id": "arcon:weapon_missile_launcher",
    "tab": "weapons",
    "image": "turMissile.png"
  },
  {
    "id": "arcon:weapon_artillery_launcher",
    "tab": "weapons",
    "image": "turLong1.png"
  },
  {
    "id": "arcon:weapon_sidewinder_launcher",
    "tab": "weapons",
    "image": "turMine.png"
  },
  {
    "id": "arcon:weapon_plasma_double_cannon",
    "tab": "weapons",
    "image": "turPlasma.png"
  },
  {
    "id": "arcon:weapon_plasma_cannon",
    "disabled": true,
    "tab": "weapons",
    "image": "turPlasma.png"
  },
  {
    "id": "arcon:weapon_light_beam",
    "tab": "weapons",
    "image": "turBeam2.png"
  },
  {
    "id": "arcon:weapon_heavy_beam",
    "tab": "weapons",
    "image": "turBeam1.png"
  },
  {
    "id": "arcon:weapon_flak_cannon",
    "tab": "weapons",
    "image": "turFlack.png"
  },
  {
    "id": "arcon:weapon_legacy_sniper_gun",
    "disabled": true,
    "tab": "weapons",
    "image": "turSnipe1.png"
  },
  {
    "id": "arcon:weapon_emp_gun",
    "tab": "weapons",
    "image": "turEMP.png"
  },
  {
    "id": "arcon:weapon_orb_dispenser",
    "tab": "weapons",
    "image": "turFizzleGun.png"
  },
  {
    "id": "arcon:weapon_phase_bomb_launcher",
    "tab": "weapons",
    "image": "turBomb.png"
  },
  {
    "id": "arcon:weapon_burst_autocannon",
    "tab": "weapons",
    "image": "turAutoCannon.png"
  },
  {
    "id": "arcon:weapon_legacy_shotgun",
    "translate_key_desc": "weapon_burst_autocannon",
    "disabled": true,
    "tab": "weapons",
    "image": "turAutoCannon.png"
  },
  {
    "id": "arcon:weapon_legacy_machinegun",
    "disabled": true,
    "tab": "weapons",
    "image": "turAutoCannon.png"
  },
  {
    "id": "arcon:weapon_arcing_tesla_projector",
    "tab": "weapons",
    "image": "turTesla.png"
  },
  {
    "id": "arcon:weapon_kinetic_wave_pull",
    "tab": "weapons",
    "image": "turWavePull.png"
  },
  {
    "id": "arcon:weapon_kinetic_wave_push",
    "tab": "weapons",
    "image": "turWavePush.png"
  },
  {
    "id": "arcon:weapon_flamethrower",
    "tab": "weapons",
    "image": "turFlame.png"
  },
  {
    "id": "arcon:warhead_blast",
    "tab": "defence",
    "image": "AOEWarhead.png"
  },
  {
    "id": "arcon:warhead_emp",
    "tab": "defence",
    "image": "empField.png"
  },
  {
    "id": "arcon:warhead_flame",
    "disabled": true,
    "tab": "defence",
    "image": "pad2x2.png"
  },
  {
    "id": "arcon:warhead_shaped",
    "tab": "defence",
    "image": "ShapedWarhead.png"
  },
  {
    "id": "arcon:weaponmod_range",
    "tab": "weapons",
    "image": "TargetingMod.png"
  },
  {
    "id": "arcon:weaponmod_damage",
    "tab": "weapons",
    "image": "DamageMod.png"
  },
  {
    "id": "arcon:weaponmod_reload",
    "tab": "weapons",
    "image": "ReloaderMod.png"
  },
  {
    "id": "arcon:weaponmod_speed",
    "tab": "weapons",
    "image": "BulletSpeedMod.png"
  },
  {
    "id": "arcon:weaponmod_energy",
    "tab": "weapons",
    "image": "dampener.png"
  },
  {
    "id": "arcon:weaponmod_ai_1",
    "disabled": true,
    "tab": "weapons",
    "image": "ai01.png"
  },
  {
    "id": "arcon:weaponmod_ai_2",
    "tab": "weapons",
    "image": "OverKillAi.png"
  },
  {
    "id": "arcon:weaponmod_ai_3",
    "disabled": true,
    "tab": "weapons",
    "image": "ai09.png"
  },
  {
    "id": "arcon:weaponmod_ai_4",
    "disabled": true,
    "tab": "weapons",
    "image": "ai03.png"
  },
  {
    "id": "arcon:decal_symbol_1",
    "translate_key_name": "decal_symbol",
    "translate_key_desc": "decal_symbol",
    "tab": "decal",
    "image": "decals/Symbol1.png"
  },
  {
    "id": "arcon:decal_symbol_2",
    "translate_key_name": "decal_symbol",
    "translate_key_desc": "decal_symbol",
    "tab": "decal",
    "image": "decals/Symbol2.png"
  },
  {
    "id": "arcon:decal_symbol_3",
    "translate_key_name": "decal_symbol",
    "translate_key_desc": "decal_symbol",
    "tab": "decal",
    "image": "decals/Symbol3.png"
  },
  {
    "id": "arcon:decal_symbol_4",
    "translate_key_name": "decal_symbol",
    "translate_key_desc": "decal_symbol",
    "tab": "decal",
    "image": "decals/Symbol4.png"
  },
  {
    "id": "arcon:decal_symbol_5",
    "translate_key_name": "decal_symbol",
    "translate_key_desc": "decal_symbol",
    "tab": "decal",
    "image": "decals/Symbol5.png"
  },
  {
    "id": "arcon:decal_symbol_6",
    "translate_key_name": "decal_symbol",
    "translate_key_desc": "decal_symbol",
    "tab": "decal",
    "image": "decals/Symbol6.png"
  },
  {
    "id": "arcon:decal_symbol_7",
    "translate_key_name": "decal_symbol",
    "translate_key_desc": "decal_symbol",
    "tab": "decal",
    "image": "decals/Symbol7.png"
  },
  {
    "id": "arcon:decal_symbol_8",
    "translate_key_name": "decal_symbol",
    "translate_key_desc": "decal_symbol",
    "tab": "decal",
    "image": "decals/Symbol8.png"
  },
  {
    "id": "arcon:decal_symbol_9",
    "translate_key_name": "decal_symbol",
    "translate_key_desc": "decal_symbol",
    "tab": "decal",
    "image": "decals/Symbol9.png"
  },
  {
    "id": "arcon:decal_symbol_10",
    "translate_key_name": "decal_symbol",
    "translate_key_desc": "decal_symbol",
    "tab": "decal",
    "image": "decals/Symbol10.png"
  },
  {
    "id": "arcon:decal_symbol_11",
    "translate_key_name": "decal_symbol",
    "translate_key_desc": "decal_symbol",
    "tab": "decal",
    "image": "decals/Symbol11.png"
  },
  {
    "id": "arcon:decal_symbol_12",
    "translate_key_name": "decal_symbol",
    "translate_key_desc": "decal_symbol",
    "tab": "decal",
    "image": "decals/Symbol12.png"
  },
  {
    "id": "arcon:decal_symbol_13",
    "translate_key_name": "decal_symbol",
    "translate_key_desc": "decal_symbol",
    "tab": "decal",
    "image": "decals/Symbol13.png"
  },
  {
    "id": "arcon:decal_symbol_14",
    "translate_key_name": "decal_symbol",
    "translate_key_desc": "decal_symbol",
    "tab": "decal",
    "image": "decals/Symbol14.png"
  },
  {
    "id": "arcon:decal_symbol_15",
    "translate_key_name": "decal_symbol",
    "translate_key_desc": "decal_symbol",
    "tab": "decal",
    "image": "decals/Symbol15.png"
  },
  {
    "id": "arcon:decal_symbol_16",
    "translate_key_name": "decal_symbol",
    "translate_key_desc": "decal_symbol",
    "tab": "decal",
    "image": "decals/Symbol16.png"
  },
  {
    "id": "arcon:decal_symbol_17",
    "translate_key_name": "decal_symbol",
    "translate_key_desc": "decal_symbol",
    "tab": "decal",
    "image": "decals/Symbol17.png"
  },
  {
    "id": "arcon:decal_symbol_18",
    "translate_key_name": "decal_symbol",
    "translate_key_desc": "decal_symbol",
    "tab": "decal",
    "image": "decals/Symbol18.png"
  },
  {
    "id": "arcon:decal_symbol_19",
    "translate_key_name": "decal_symbol",
    "translate_key_desc": "decal_symbol",
    "tab": "decal",
    "image": "decals/Symbol19.png"
  },
  {
    "id": "arcon:decal_symbol_20",
    "translate_key_name": "decal_symbol",
    "translate_key_desc": "decal_symbol",
    "tab": "decal",
    "image": "decals/Symbol20.png"
  },
  {
    "id": "arcon:decal_symbol_21",
    "translate_key_name": "decal_symbol",
    "translate_key_desc": "decal_symbol",
    "tab": "decal",
    "image": "decals/Symbol21.png"
  },
  {
    "id": "arcon:decal_symbol_22",
    "translate_key_name": "decal_symbol",
    "translate_key_desc": "decal_symbol",
    "tab": "decal",
    "image": "decals/Symbol22.png"
  },
  {
    "id": "arcon:decal_symbol_23",
    "translate_key_name": "decal_symbol",
    "translate_key_desc": "decal_symbol",
    "tab": "decal",
    "image": "decals/Symbol23.png"
  },
  {
    "id": "arcon:decal_symbol_24",
    "translate_key_name": "decal_symbol",
    "translate_key_desc": "decal_symbol",
    "tab": "decal",
    "image": "decals/Symbol24.png"
  },
  {
    "id": "arcon:decal_symbol_25",
    "translate_key_name": "decal_symbol",
    "translate_key_desc": "decal_symbol",
    "tab": "decal",
    "image": "decals/Symbol25.png"
  },
  {
    "id": "arcon:decal_symbol_26",
    "translate_key_name": "decal_symbol",
    "translate_key_desc": "decal_symbol",
    "tab": "decal",
    "image": "decals/Symbol26.png"
  },
  {
    "id": "arcon:decal_symbol_27",
    "translate_key_name": "decal_symbol",
    "translate_key_desc": "decal_symbol",
    "tab": "decal",
    "image": "decals/Symbol27.png"
  },
  {
    "id": "arcon:decal_symbol_28",
    "translate_key_name": "decal_symbol",
    "translate_key_desc": "decal_symbol",
    "tab": "decal",
    "image": "decals/Symbol28.png"
  },
  {
    "id": "arcon:decal_symbol_29",
    "translate_key_name": "decal_symbol",
    "translate_key_desc": "decal_symbol",
    "disabled": true,
    "tab": "decal",
    "image": "decals/Symbol29.png"
  },
  {
    "id": "arcon:decal_symbol_30",
    "translate_key_name": "decal_symbol",
    "translate_key_desc": "decal_symbol",
    "disabled": true,
    "tab": "decal",
    "image": "decals/Symbol30.png"
  },
  {
    "id": "arcon:decal_symbol_31",
    "translate_key_name": "decal_symbol",
    "translate_key_desc": "decal_symbol",
    "disabled": true,
    "tab": "decal",
    "image": "decals/Symbol31.png"
  },
  {
    "id": "arcon:decal_symbol_32",
    "translate_key_name": "decal_symbol",
    "translate_key_desc": "decal_symbol",
    "disabled": true,
    "tab": "decal",
    "image": "decals/Symbol32.png"
  },
  {
    "id": "arcon:decal_symbol_33",
    "translate_key_name": "decal_symbol",
    "translate_key_desc": "decal_symbol",
    "disabled": true,
    "tab": "decal",
    "image": "decals/Symbol33.png"
  },
  {
    "id": "arcon:decal_symbol_34",
    "translate_key_name": "decal_symbol",
    "translate_key_desc": "decal_symbol",
    "disabled": true,
    "tab": "decal",
    "image": "decals/Symbol34.png"
  },
  {
    "id": "arcon:decal_symbol_35",
    "translate_key_name": "decal_symbol",
    "translate_key_desc": "decal_symbol",
    "disabled": true,
    "tab": "decal",
    "image": "decals/Symbol35.png"
  },
  {
    "id": "arcon:decal_symbol_36",
    "translate_key_name": "decal_symbol",
    "translate_key_desc": "decal_symbol",
    "disabled": true,
    "tab": "decal",
    "image": "decals/Symbol36.png"
  },
  {
    "id": "arcon:decal_symbol_37",
    "translate_key_name": "decal_symbol",
    "translate_key_desc": "decal_symbol",
    "disabled": true,
    "tab": "decal",
    "image": "decals/Symbol37.png"
  },
  {
    "id": "arcon:decal_symbol_38",
    "translate_key_name": "decal_symbol",
    "translate_key_desc": "decal_symbol",
    "disabled": true,
    "tab": "decal",
    "image": "decals/Symbol38.png"
  },
  {
    "id": "arcon:decal_symbol_39",
    "translate_key_name": "decal_symbol",
    "translate_key_desc": "decal_symbol",
    "disabled": true,
    "tab": "decal",
    "image": "decals/Symbol39.png"
  },
  {
    "id": "arcon:decal_symbol_40",
    "translate_key_name": "decal_symbol",
    "translate_key_desc": "decal_symbol",
    "disabled": true,
    "tab": "decal",
    "image": "decals/Symbol40.png"
  },
  {
    "id": "arcon:decal_stripe_1x1",
    "translate_key_name": "decal_stripe",
    "translate_key_desc": "decal_stripe",
    "tab": "stripes",
    "image": "decals/Stripe1x1.png"
  },
  {
    "id": "arcon:decal_stripe_1x1_corner",
    "translate_key_name": "decal_stripe",
    "translate_key_desc": "decal_stripe",
    "tab": "stripes",
    "image": "decals/Stripe1x1Corner.png"
  },
  {
    "id": "arcon:decal_stripe_1x2",
    "translate_key_name": "decal_stripe",
    "translate_key_desc": "decal_stripe",
    "tab": "stripes",
    "image": "decals/Stripe1x2.png"
  },
  {
    "id": "arcon:decal_stripe_2x1",
    "translate_key_name": "decal_stripe",
    "translate_key_desc": "decal_stripe",
    "tab": "stripes",
    "image": "decals/Stripe2x1.png"
  },
  {
    "id": "arcon:decal_stripe_2x2",
    "translate_key_name": "decal_stripe",
    "translate_key_desc": "decal_stripe",
    "tab": "stripes",
    "image": "decals/Stripe2x2.png"
  },
  {
    "id": "arcon:decal_stripe_2x2_corner",
    "translate_key_name": "decal_stripe",
    "translate_key_desc": "decal_stripe",
    "tab": "stripes",
    "image": "decals/Stripe2x2Corner.png"
  },
  {
    "id": "arcon:decal_stripe_2x2_round",
    "translate_key_name": "decal_stripe",
    "translate_key_desc": "decal_stripe",
    "tab": "stripes",
    "image": "decals/Stripe2x2Round.png"
  },
  {
    "id": "arcon:decal_stripe_double_2x1",
    "translate_key_name": "decal_stripe",
    "translate_key_desc": "decal_stripe",
    "tab": "stripes",
    "image": "decals/StripeDouble2x1.png"
  },
  {
    "id": "arcon:decal_stripe_double_2x2",
    "translate_key_name": "decal_stripe",
    "translate_key_desc": "decal_stripe",
    "tab": "stripes",
    "image": "decals/StripeDouble2x2.png"
  },
  {
    "id": "arcon:decal_stripe_1x1_slash",
    "translate_key_name": "decal_stripe",
    "translate_key_desc": "decal_stripe",
    "tab": "stripes",
    "image": "decals/Stripe1x1Slash.png"
  },
  {
    "id": "arcon:decal_stripe_1x1_slash_inside",
    "translate_key_name": "decal_stripe",
    "translate_key_desc": "decal_stripe",
    "tab": "stripes",
    "image": "decals/Stripe1x1SlashInside.png"
  },
  {
    "id": "arcon:decal_stripe_2x2_slash",
    "translate_key_name": "decal_stripe",
    "translate_key_desc": "decal_stripe",
    "tab": "stripes",
    "image": "decals/Stripe2x2Slash.png"
  },
  {
    "id": "arcon:decal_stripe_2x2_end",
    "translate_key_name": "decal_stripe",
    "translate_key_desc": "decal_stripe",
    "tab": "stripes",
    "image": "decals/Stripe2x2End.png"
  },
  {
    "id": "arcon:decal_stripe_1x1_fill1",
    "translate_key_name": "decal_stripe",
    "translate_key_desc": "decal_stripe",
    "tab": "stripes",
    "image": "decals/Stripe1x1Fill1.png"
  },
  {
    "id": "arcon:decal_stripe_1x1_fill2",
    "translate_key_name": "decal_stripe",
    "translate_key_desc": "decal_stripe",
    "tab": "stripes",
    "image": "decals/Stripe1x1Fill2.png"
  },
  {
    "id": "arcon:decal_stripe_1x1_fill3",
    "translate_key_name": "decal_stripe",
    "translate_key_desc": "decal_stripe",
    "tab": "stripes",
    "image": "decals/Stripe1x1Fill3.png"
  },
  {
    "id": "arcon:decal_stripe_1x1_fill4",
    "translate_key_name": "decal_stripe",
    "translate_key_desc": "decal_stripe",
    "tab": "stripes",
    "image": "decals/Stripe1x1Fill4.png"
  },
  {
    "id": "arcon:decal_stripe_1x1_fill5",
    "translate_key_name": "decal_stripe",
    "translate_key_desc": "decal_stripe",
    "tab": "stripes",
    "image": "decals/Stripe1x1Fill5.png"
  },
  {
    "id": "arcon:decal_stripe_1x1_fill6",
    "translate_key_name": "decal_stripe",
    "translate_key_desc": "decal_stripe",
    "tab": "stripes",
    "image": "decals/Stripe1x1Fill6.png"
  },
  {
    "id": "arcon:decal_letter_a",
    "translate_key_name": "decal_letter",
    "translate_key_desc": "decal_letter",
    "tab": "letters",
    "image": "decals/letterA.png"
  },
  {
    "id": "arcon:decal_letter_b",
    "translate_key_name": "decal_letter",
    "translate_key_desc": "decal_letter",
    "tab": "letters",
    "image": "decals/letterB.png"
  },
  {
    "id": "arcon:decal_letter_c",
    "translate_key_name": "decal_letter",
    "translate_key_desc": "decal_letter",
    "tab": "letters",
    "image": "decals/letterC.png"
  },
  {
    "id": "arcon:decal_letter_d",
    "translate_key_name": "decal_letter",
    "translate_key_desc": "decal_letter",
    "tab": "letters",
    "image": "decals/letterD.png"
  },
  {
    "id": "arcon:decal_letter_e",
    "translate_key_name": "decal_letter",
    "translate_key_desc": "decal_letter",
    "tab": "letters",
    "image": "decals/letterE.png"
  },
  {
    "id": "arcon:decal_letter_f",
    "translate_key_name": "decal_letter",
    "translate_key_desc": "decal_letter",
    "tab": "letters",
    "image": "decals/letterF.png"
  },
  {
    "id": "arcon:decal_letter_g",
    "translate_key_name": "decal_letter",
    "translate_key_desc": "decal_letter",
    "tab": "letters",
    "image": "decals/letterG.png"
  },
  {
    "id": "arcon:decal_letter_h",
    "translate_key_name": "decal_letter",
    "translate_key_desc": "decal_letter",
    "tab": "letters",
    "image": "decals/letterH.png"
  },
  {
    "id": "arcon:decal_letter_i",
    "translate_key_name": "decal_letter",
    "translate_key_desc": "decal_letter",
    "tab": "letters",
    "image": "decals/letterI.png"
  },
  {
    "id": "arcon:decal_letter_j",
    "translate_key_name": "decal_letter",
    "translate_key_desc": "decal_letter",
    "tab": "letters",
    "image": "decals/letterJ.png"
  },
  {
    "id": "arcon:decal_letter_k",
    "translate_key_name": "decal_letter",
    "translate_key_desc": "decal_letter",
    "tab": "letters",
    "image": "decals/letterK.png"
  },
  {
    "id": "arcon:decal_letter_l",
    "translate_key_name": "decal_letter",
    "translate_key_desc": "decal_letter",
    "tab": "letters",
    "image": "decals/letterL.png"
  },
  {
    "id": "arcon:decal_letter_m",
    "translate_key_name": "decal_letter",
    "translate_key_desc": "decal_letter",
    "tab": "letters",
    "image": "decals/letterM.png"
  },
  {
    "id": "arcon:decal_letter_n",
    "translate_key_name": "decal_letter",
    "translate_key_desc": "decal_letter",
    "tab": "letters",
    "image": "decals/letterN.png"
  },
  {
    "id": "arcon:decal_letter_o",
    "translate_key_name": "decal_letter",
    "translate_key_desc": "decal_letter",
    "tab": "letters",
    "image": "decals/letterO.png"
  },
  {
    "id": "arcon:decal_letter_p",
    "translate_key_name": "decal_letter",
    "translate_key_desc": "decal_letter",
    "tab": "letters",
    "image": "decals/letterP.png"
  },
  {
    "id": "arcon:decal_letter_q",
    "translate_key_name": "decal_letter",
    "translate_key_desc": "decal_letter",
    "tab": "letters",
    "image": "decals/letterQ.png"
  },
  {
    "id": "arcon:decal_letter_r",
    "translate_key_name": "decal_letter",
    "translate_key_desc": "decal_letter",
    "tab": "letters",
    "image": "decals/letterR.png"
  },
  {
    "id": "arcon:decal_letter_s",
    "translate_key_name": "decal_letter",
    "translate_key_desc": "decal_letter",
    "tab": "letters",
    "image": "decals/letterS.png"
  },
  {
    "id": "arcon:decal_letter_t",
    "translate_key_name": "decal_letter",
    "translate_key_desc": "decal_letter",
    "tab": "letters",
    "image": "decals/letterT.png"
  },
  {
    "id": "arcon:decal_letter_u",
    "translate_key_name": "decal_letter",
    "translate_key_desc": "decal_letter",
    "tab": "letters",
    "image": "decals/letterU.png"
  },
  {
    "id": "arcon:decal_letter_v",
    "translate_key_name": "decal_letter",
    "translate_key_desc": "decal_letter",
    "tab": "letters",
    "image": "decals/letterV.png"
  },
  {
    "id": "arcon:decal_letter_w",
    "translate_key_name": "decal_letter",
    "translate_key_desc": "decal_letter",
    "tab": "letters",
    "image": "decals/letterW.png"
  },
  {
    "id": "arcon:decal_letter_x",
    "translate_key_name": "decal_letter",
    "translate_key_desc": "decal_letter",
    "tab": "letters",
    "image": "decals/letterX.png"
  },
  {
    "id": "arcon:decal_letter_y",
    "translate_key_name": "decal_letter",
    "translate_key_desc": "decal_letter",
    "tab": "letters",
    "image": "decals/letterY.png"
  },
  {
    "id": "arcon:decal_letter_z",
    "translate_key_name": "decal_letter",
    "translate_key_desc": "decal_letter",
    "tab": "letters",
    "image": "decals/letterZ.png"
  },
  {
    "id": "arcon:decal_letter_pound",
    "translate_key_name": "decal_letter",
    "translate_key_desc": "decal_letter",
    "tab": "letters",
    "image": "decals/letterPound.png"
  },
  {
    "id": "arcon:decal_letter_dot",
    "translate_key_name": "decal_letter",
    "translate_key_desc": "decal_letter",
    "tab": "letters",
    "image": "decals/letterDot.png"
  },
  {
    "id": "arcon:decal_letter_0",
    "translate_key_name": "decal_letter",
    "translate_key_desc": "decal_letter",
    "tab": "letters",
    "image": "decals/letter0.png"
  },
  {
    "id": "arcon:decal_letter_1",
    "translate_key_name": "decal_letter",
    "translate_key_desc": "decal_letter",
    "tab": "letters",
    "image": "decals/letter1.png"
  },
  {
    "id": "arcon:decal_letter_2",
    "translate_key_name": "decal_letter",
    "translate_key_desc": "decal_letter",
    "tab": "letters",
    "image": "decals/letter2.png"
  },
  {
    "id": "arcon:decal_letter_3",
    "translate_key_name": "decal_letter",
    "translate_key_desc": "decal_letter",
    "tab": "letters",
    "image": "decals/letter3.png"
  },
  {
    "id": "arcon:decal_letter_4",
    "translate_key_name": "decal_letter",
    "translate_key_desc": "decal_letter",
    "tab": "letters",
    "image": "decals/letter4.png"
  },
  {
    "id": "arcon:decal_letter_5",
    "translate_key_name": "decal_letter",
    "translate_key_desc": "decal_letter",
    "tab": "letters",
    "image": "decals/letter5.png"
  },
  {
    "id": "arcon:decal_letter_6",
    "translate_key_name": "decal_letter",
    "translate_key_desc": "decal_letter",
    "tab": "letters",
    "image": "decals/letter6.png"
  },
  {
    "id": "arcon:decal_letter_7",
    "translate_key_name": "decal_letter",
    "translate_key_desc": "decal_letter",
    "tab": "letters",
    "image": "decals/letter7.png"
  },
  {
    "id": "arcon:decal_letter_8",
    "translate_key_name": "decal_letter",
    "translate_key_desc": "decal_letter",
    "tab": "letters",
    "image": "decals/letter8.png"
  },
  {
    "id": "arcon:decal_letter_9",
    "translate_key_name": "decal_letter",
    "translate_key_desc": "decal_letter",
    "tab": "letters",
    "image": "decals/letter9.png"
  },
  {
    "id": "arcon:faction_insignia_dev",
    "translate_key_name": "faction_insignia",
    "translate_key_desc": "faction_insignia",
    "disabled": true,
    "tab": "decal",
    "image": "factions/DEV.png"
  },
  {
    "id": "arcon:faction_insignia_mod",
    "translate_key_name": "faction_insignia",
    "translate_key_desc": "faction_insignia",
    "disabled": true,
    "tab": "decal",
    "image": "factions/MOD.png"
  },
  {
    "id": "arcon:faction_insignia_kc",
    "translate_key_name": "faction_insignia",
    "translate_key_desc": "faction_insignia",
    "disabled": true,
    "tab": "decal",
    "image": "factions/KC.png"
  },
  {
    "id": "arcon:faction_insignia_auto",
    "translate_key_name": "faction_insignia",
    "translate_key_desc": "faction_insignia",
    "disabled": true,
    "tab": "decal",
    "image": "factions/AUTO.png"
  },
  {
    "id": "arcon:faction_insignia_sieg",
    "translate_key_name": "faction_insignia",
    "translate_key_desc": "faction_insignia",
    "disabled": true,
    "tab": "decal",
    "image": "factions/SIEG.png"
  },
  {
    "id": "arcon:faction_insignia_isoi",
    "translate_key_name": "faction_insignia",
    "translate_key_desc": "faction_insignia",
    "disabled": true,
    "tab": "decal",
    "image": "factions/ISOI.png"
  },
  {
    "id": "arcon:faction_insignia_tkka",
    "translate_key_name": "faction_insignia",
    "translate_key_desc": "faction_insignia",
    "disabled": true,
    "tab": "decal",
    "image": "factions/TKKA.png"
  }
]
